{
  "Topic": {
    "TopicId": "5832",
    "ForumId": "10",
    "Title": "New Language?",
    "LastUpdated": "2016-01-21T22:45:15+00:00",
    "ReplyCount": 2
  },
  "Posts": [
    {
      "PostId": "40352",
      "UserId": 0,
      "Username": "Coifi",
      "UserAvatar": null,
      "UserGravatar": "febccdc1db2ea7c7045645cc2d59f192",
      "EditableText": "I hope this hasn't already been asked but I couldn't find it.\n\nI am really excited to make game in Quest to help me and others learn Old English (Anglo Saxon) \nBut I will need the prompt and commands to be in OE too.\n\nHow can I add a language to the list for use in the interface?\n\nGo north - far norþ\nTake the seax - Nim þæt sēax \n\netc\n Also I really need all the characters to show up\n\næǣeēþðÞÐȳ etc\n\nThanks for your help",
      "EditableFormat": "bbcode",
      "HTML": "I hope this hasn't already been asked but I couldn't find it.<br/><br/>I am really excited to make game in Quest to help me and others learn Old English (Anglo Saxon) <br/>But I will need the prompt and commands to be in OE too.<br/><br/>How can I add a language to the list for use in the interface?<br/><br/>Go north - far norþ<br/>Take the seax - Nim þæt sēax <br/><br/>etc<br/> Also I really need all the characters to show up<br/><br/>æǣeēþðÞÐȳ etc<br/><br/>Thanks for your help",
      "PostDate": "2016-01-08T11:30:56+00:00",
      "LastEditDate": null
    },
    {
      "PostId": "40353",
      "UserId": 0,
      "Username": "Alex",
      "UserAvatar": null,
      "UserGravatar": "188b72c5e13327f4fde3989dca7d7d53",
      "EditableText": "You can find all the info you need here: <!-- m --><a class=\"postlink\" href=\"http://docs.textadventures.co.uk/quest/guides/translating_quest.html\">http://docs.textadventures.co.uk/quest/ ... quest.html</a><!-- m -->",
      "EditableFormat": "bbcode",
      "HTML": "You can find all the info you need here: <!-- m --><a class=\"postlink\" href=\"http://docs.textadventures.co.uk/quest/guides/translating_quest.html\">http://docs.textadventures.co.uk/quest/ ... quest.html</a><!-- m -->",
      "PostDate": "2016-01-08T11:54:25+00:00",
      "LastEditDate": null
    },
    {
      "PostId": "40857",
      "UserId": 0,
      "Username": "Coifi",
      "UserAvatar": null,
      "UserGravatar": "febccdc1db2ea7c7045645cc2d59f192",
      "EditableText": "Thank you! I'll study this....",
      "EditableFormat": "bbcode",
      "HTML": "Thank you! I'll study this....",
      "PostDate": "2016-01-21T22:45:15+00:00",
      "LastEditDate": null
    }
  ]
}
