{
  "Topic": {
    "TopicId": "1562",
    "ForumId": "3",
    "Title": "New Website",
    "LastUpdated": "2007-01-24T09:34:48+00:00",
    "ReplyCount": 14
  },
  "Posts": [
    {
      "PostId": "12212",
      "UserId": 0,
      "Username": "GameBoy",
      "UserAvatar": null,
      "UserGravatar": "554e89a053350b96f686f324a6049e9d",
      "EditableText": "Didn't know where else to post this since there isn't really a general discussion forum for Quest.  But the website looks great.  I've been here for a long time and don't remember there ever being a huge change in the website.\n\nGood job Alex  <!-- s:D --><img src=\"{SMILIES_PATH}/icon_e_biggrin.gif\" alt=\":D\" title=\"Very Happy\" /><!-- s:D -->",
      "EditableFormat": "bbcode",
      "HTML": "Didn't know where else to post this since there isn't really a general discussion forum for Quest.  But the website looks great.  I've been here for a long time and don't remember there ever being a huge change in the website.<br/><br/>Good job Alex  <!-- s:D --><img src=\"{SMILIES_PATH}/icon_e_biggrin.gif\" alt=\":D\" title=\"Very Happy\" /><!-- s:D -->",
      "PostDate": "2007-01-17T17:35:01+00:00",
      "LastEditDate": null
    },
    {
      "PostId": "12213",
      "UserId": 0,
      "Username": "Alex",
      "UserAvatar": null,
      "UserGravatar": "188b72c5e13327f4fde3989dca7d7d53",
      "EditableText": "Cheers, I'm rather fond of it myself...",
      "EditableFormat": "bbcode",
      "HTML": "Cheers, I'm rather fond of it myself...",
      "PostDate": "2007-01-17T17:58:44+00:00",
      "LastEditDate": null
    },
    {
      "PostId": "12218",
      "UserId": 0,
      "Username": "paul_one",
      "UserAvatar": null,
      "UserGravatar": "fef8a1875028f4300bb683f29c432894",
      "EditableText": "I have to agree... Although I do remember that the last site was a redesign/simplification on a previous website.\n\nLooks nice, but the changing menu buttons aren't good for me... I guess I just got so used to the old design..",
      "EditableFormat": "bbcode",
      "HTML": "I have to agree... Although I do remember that the last site was a redesign/simplification on a previous website.<br/><br/>Looks nice, but the changing menu buttons aren't good for me... I guess I just got so used to the old design..",
      "PostDate": "2007-01-17T19:36:57+00:00",
      "LastEditDate": null
    },
    {
      "PostId": "12223",
      "UserId": 0,
      "Username": "GameBoy",
      "UserAvatar": null,
      "UserGravatar": "554e89a053350b96f686f324a6049e9d",
      "EditableText": "Awwh, it's sad to see drastic changes to something you've spend years being used to, but I actually prefer this new design, except one little thing.\nOn this page: <!-- m --><a class=\"postlink\" href=\"http://www.axeuk.com/quest/\">http://www.axeuk.com/quest/</a><!-- m --> the box on the right takes up a lot of room when it could be located underneath the main text, or make smaller.  I just think it would look better, give the main text more space, so it's easier to read.",
      "EditableFormat": "bbcode",
      "HTML": "Awwh, it's sad to see drastic changes to something you've spend years being used to, but I actually prefer this new design, except one little thing.<br/>On this page: <!-- m --><a class=\"postlink\" href=\"http://www.axeuk.com/quest/\">http://www.axeuk.com/quest/</a><!-- m --> the box on the right takes up a lot of room when it could be located underneath the main text, or make smaller.  I just think it would look better, give the main text more space, so it's easier to read.",
      "PostDate": "2007-01-17T22:44:55+00:00",
      "LastEditDate": null
    },
    {
      "PostId": "12226",
      "UserId": 0,
      "Username": "paul_one",
      "UserAvatar": null,
      "UserGravatar": "fef8a1875028f4300bb683f29c432894",
      "EditableText": "^^\nDon't you mean &quot;excuse my drunk - I'm English!&quot; <!-- s:D --><img src=\"{SMILIES_PATH}/icon_e_biggrin.gif\" alt=\":D\" title=\"Very Happy\" /><!-- s:D --> .\n\n.. I also see you're having MSN prob's too.. I was stuck using my nick to talk to one of my friends for a fair bit... I haven't talked to her in AGES either!",
      "EditableFormat": "bbcode",
      "HTML": "^^<br/>Don't you mean &quot;excuse my drunk - I'm English!&quot; <!-- s:D --><img src=\"{SMILIES_PATH}/icon_e_biggrin.gif\" alt=\":D\" title=\"Very Happy\" /><!-- s:D --> .<br/><br/>.. I also see you're having MSN prob's too.. I was stuck using my nick to talk to one of my friends for a fair bit... I haven't talked to her in AGES either!",
      "PostDate": "2007-01-17T22:54:14+00:00",
      "LastEditDate": null
    },
    {
      "PostId": "12233",
      "UserId": 0,
      "Username": "GameBoy",
      "UserAvatar": null,
      "UserGravatar": "554e89a053350b96f686f324a6049e9d",
      "EditableText": "lol, yeah. Just sometimes I'll type things like making instead of makes, or changed instead of changes, just little errors like that.  But I'm not English so it wouldn't work the other way <!-- s:P --><img src=\"{SMILIES_PATH}/icon_razz.gif\" alt=\":P\" title=\"Razz\" /><!-- s:P -->\n\nAnd yes, looks like everybody was having problems.",
      "EditableFormat": "bbcode",
      "HTML": "lol, yeah. Just sometimes I'll type things like making instead of makes, or changed instead of changes, just little errors like that.  But I'm not English so it wouldn't work the other way <!-- s:P --><img src=\"{SMILIES_PATH}/icon_razz.gif\" alt=\":P\" title=\"Razz\" /><!-- s:P --><br/><br/>And yes, looks like everybody was having problems.",
      "PostDate": "2007-01-18T09:47:17+00:00",
      "LastEditDate": null
    },
    {
      "PostId": "12298",
      "UserId": 0,
      "Username": "Elexxorine",
      "UserAvatar": null,
      "UserGravatar": "a220ee44d8fe2f07029cf1f61b98bf40",
      "EditableText": "Steve, you're welsh, that hardly let's you pull the 'I'm not English' card, that's for people who have English as a second language, and I know you can't speak welsh, so don't try to pull anything over on that one either. lol.",
      "EditableFormat": "bbcode",
      "HTML": "Steve, you're welsh, that hardly let's you pull the 'I'm not English' card, that's for people who have English as a second language, and I know you can't speak welsh, so don't try to pull anything over on that one either. lol.",
      "PostDate": "2007-01-20T14:12:42+00:00",
      "LastEditDate": null
    },
    {
      "PostId": "12320",
      "UserId": 0,
      "Username": "007bond",
      "UserAvatar": null,
      "UserGravatar": "4c2673a2d8666a97b5c1082c5cf2e0e5",
      "EditableText": "Gotta agree with GameBoy, the new site looks awesome.\nIt definitely looks a lot better.",
      "EditableFormat": "bbcode",
      "HTML": "Gotta agree with GameBoy, the new site looks awesome.<br/>It definitely looks a lot better.",
      "PostDate": "2007-01-22T16:56:34+00:00",
      "LastEditDate": null
    },
    {
      "PostId": "12342",
      "UserId": 0,
      "Username": "GameBoy",
      "UserAvatar": null,
      "UserGravatar": "554e89a053350b96f686f324a6049e9d",
      "EditableText": "[quote=&quot;elexxorine&quot;:205pmyjf]Steve, you're welsh, that hardly let's you pull the 'I'm not English' card, that's for people who have English as a second language, and I know you can't speak welsh, so don't try to pull anything over on that one either. lol.[/quote:205pmyjf]\n\nActually, yes I can speak Welsh, and yes I had a Welsh accent, and no I'm not English, I was raised in North Wales <!-- s:) --><img src=\"{SMILIES_PATH}/icon_e_smile.gif\" alt=\":)\" title=\"Smile\" /><!-- s:) -->  Get the facts right <!-- s;) --><img src=\"{SMILIES_PATH}/icon_e_wink.gif\" alt=\";)\" title=\"Wink\" /><!-- s;) -->",
      "EditableFormat": "bbcode",
      "HTML": "<blockquote><cite>elexxorine wrote:</cite>Steve, you're welsh, that hardly let's you pull the 'I'm not English' card, that's for people who have English as a second language, and I know you can't speak welsh, so don't try to pull anything over on that one either. lol.</blockquote><br/><br/>Actually, yes I can speak Welsh, and yes I had a Welsh accent, and no I'm not English, I was raised in North Wales <!-- s:) --><img src=\"{SMILIES_PATH}/icon_e_smile.gif\" alt=\":)\" title=\"Smile\" /><!-- s:) -->  Get the facts right <!-- s;) --><img src=\"{SMILIES_PATH}/icon_e_wink.gif\" alt=\";)\" title=\"Wink\" /><!-- s;) -->",
      "PostDate": "2007-01-22T18:58:04+00:00",
      "LastEditDate": null
    },
    {
      "PostId": "12362",
      "UserId": 0,
      "Username": "Elexxorine",
      "UserAvatar": null,
      "UserGravatar": "a220ee44d8fe2f07029cf1f61b98bf40",
      "EditableText": "Where were your parents bron? If we're going to do this properly.... My nephew says he's welsh but he's actually only 3/8 welsh, his grandparents being welsh/half welsh (making technically welsh father) and not/not (makinc british mother. So if we're doing this properly for example my nephow wouldn't count as welsh, barely as half...... lol. So what is it Steve?",
      "EditableFormat": "bbcode",
      "HTML": "Where were your parents bron? If we're going to do this properly.... My nephew says he's welsh but he's actually only 3/8 welsh, his grandparents being welsh/half welsh (making technically welsh father) and not/not (makinc british mother. So if we're doing this properly for example my nephow wouldn't count as welsh, barely as half...... lol. So what is it Steve?",
      "PostDate": "2007-01-22T20:53:13+00:00",
      "LastEditDate": null
    },
    {
      "PostId": "12365",
      "UserId": 0,
      "Username": "GameBoy",
      "UserAvatar": null,
      "UserGravatar": "554e89a053350b96f686f324a6049e9d",
      "EditableText": "My Dad is Welsh, his Dad was Welsh, my Nan is Irish though, my Mom is English.  But I don't believe in all that &quot;3/4 Welsh&quot; crap.  Blood isn't any different depending on where you were born, plus, my nationality is technically British, as that's what it would say on a passport.  But I was born and raised in Wales, and that makes me Welsh by origin.\n\nAlso, the fact that I wasn't talking about my origin makes this conversation even more pointless, as I was talking about the language.",
      "EditableFormat": "bbcode",
      "HTML": "My Dad is Welsh, his Dad was Welsh, my Nan is Irish though, my Mom is English.  But I don't believe in all that &quot;3/4 Welsh&quot; crap.  Blood isn't any different depending on where you were born, plus, my nationality is technically British, as that's what it would say on a passport.  But I was born and raised in Wales, and that makes me Welsh by origin.<br/><br/>Also, the fact that I wasn't talking about my origin makes this conversation even more pointless, as I was talking about the language.",
      "PostDate": "2007-01-23T01:09:57+00:00",
      "LastEditDate": null
    },
    {
      "PostId": "12375",
      "UserId": 0,
      "Username": "paul_one",
      "UserAvatar": null,
      "UserGravatar": "fef8a1875028f4300bb683f29c432894",
      "EditableText": "^^ Nationality is where you are BORN.. Also where you emmigrate to - but even then, you're still the nationality of where you are born.\n\nIf you wanna get into the whole 3/8ths welsh thing, then most European people are about 90%+ African, seeing as how we all came from the jungles of Africa a couple of million years ago.\nExcept there were native Americans - so that's the &quot;90%&quot;.\n\nIf you're born in wales - unfortunately you're Welsh <!-- s:) --><img src=\"{SMILIES_PATH}/icon_e_smile.gif\" alt=\":)\" title=\"Smile\" /><!-- s:) -->, if in Scotland, you're a drunk ginger b**, and if in England, you're a violent, football loving hooliganistic, drunken b**.",
      "EditableFormat": "bbcode",
      "HTML": "^^ Nationality is where you are BORN.. Also where you emmigrate to - but even then, you're still the nationality of where you are born.<br/><br/>If you wanna get into the whole 3/8ths welsh thing, then most European people are about 90%+ African, seeing as how we all came from the jungles of Africa a couple of million years ago.<br/>Except there were native Americans - so that's the &quot;90%&quot;.<br/><br/>If you're born in wales - unfortunately you're Welsh <!-- s:) --><img src=\"{SMILIES_PATH}/icon_e_smile.gif\" alt=\":)\" title=\"Smile\" /><!-- s:) -->, if in Scotland, you're a drunk ginger b**, and if in England, you're a violent, football loving hooliganistic, drunken b**.",
      "PostDate": "2007-01-23T11:55:17+00:00",
      "LastEditDate": null
    },
    {
      "PostId": "12382",
      "UserId": 0,
      "Username": "GameBoy",
      "UserAvatar": null,
      "UserGravatar": "554e89a053350b96f686f324a6049e9d",
      "EditableText": "Actually Tr0n, the Welsh are the real English people.  We were pushed out of England years ago during a war, that's why there is a big river seperating England and Wales, as we weren't allowed across it.\n\nI'd love to see how different this country would be if said circumstances were different.\n\nAlso, you say &quot;Unfortunately you're Welsh&quot;.  If you can name 5 [b:1q4ja1pi]REAL[/b:1q4ja1pi] things (Not just &quot;You're a sheepshagger&quot;) why being Welsh is a bad thing, i'll eat my flag.",
      "EditableFormat": "bbcode",
      "HTML": "Actually Tr0n, the Welsh are the real English people.  We were pushed out of England years ago during a war, that's why there is a big river seperating England and Wales, as we weren't allowed across it.<br/><br/>I'd love to see how different this country would be if said circumstances were different.<br/><br/>Also, you say &quot;Unfortunately you're Welsh&quot;.  If you can name 5 <span style=\"font-weight:bold;\">REAL</span> things (Not just &quot;You're a sheepshagger&quot;) why being Welsh is a bad thing, i'll eat my flag.",
      "PostDate": "2007-01-23T13:53:22+00:00",
      "LastEditDate": null
    },
    {
      "PostId": "12389",
      "UserId": 0,
      "Username": "paul_one",
      "UserAvatar": null,
      "UserGravatar": "fef8a1875028f4300bb683f29c432894",
      "EditableText": "Haha, it was a joke... That's why I said drunken Scottsman etc.\n\nI don't really care where anyone's from - unless you're Irish.. Then I REALLY have something against ya <!-- s;) --><img src=\"{SMILIES_PATH}/icon_e_wink.gif\" alt=\";)\" title=\"Wink\" /><!-- s;) --> .\n\n.. I love the Irish, so kind, drunk, sexy-sounding... I wish I were Irish!",
      "EditableFormat": "bbcode",
      "HTML": "Haha, it was a joke... That's why I said drunken Scottsman etc.<br/><br/>I don't really care where anyone's from - unless you're Irish.. Then I REALLY have something against ya <!-- s;) --><img src=\"{SMILIES_PATH}/icon_e_wink.gif\" alt=\";)\" title=\"Wink\" /><!-- s;) --> .<br/><br/>.. I love the Irish, so kind, drunk, sexy-sounding... I wish I were Irish!",
      "PostDate": "2007-01-23T17:39:17+00:00",
      "LastEditDate": null
    },
    {
      "PostId": "12409",
      "UserId": 0,
      "Username": "Elexxorine",
      "UserAvatar": null,
      "UserGravatar": "a220ee44d8fe2f07029cf1f61b98bf40",
      "EditableText": "Man, if you were Irish Tron, you would be so sexy the universe would collapse! lol.",
      "EditableFormat": "bbcode",
      "HTML": "Man, if you were Irish Tron, you would be so sexy the universe would collapse! lol.",
      "PostDate": "2007-01-24T09:34:48+00:00",
      "LastEditDate": null
    }
  ]
}
