{
  "Topic": {
    "TopicId": "1229",
    "ForumId": "3",
    "Title": "Hentai (split from Desktop)",
    "LastUpdated": "2006-07-15T01:09:05+01:00",
    "ReplyCount": 12
  },
  "Posts": [
    {
      "PostId": "9724",
      "UserId": 0,
      "Username": "headspace",
      "UserAvatar": null,
      "UserGravatar": "6bfd0ad3c32eb1200d7671af24bda653",
      "EditableText": "Do you watch a lot of hentai David?\n\nI find it a little odd after a while, all that tentacle rape stuff really gets to me.",
      "EditableFormat": "bbcode",
      "HTML": "Do you watch a lot of hentai David?<br/><br/>I find it a little odd after a while, all that tentacle rape stuff really gets to me.",
      "PostDate": "2006-07-13T22:06:49+01:00",
      "LastEditDate": null
    },
    {
      "PostId": "9726",
      "UserId": 0,
      "Username": "paul_one",
      "UserAvatar": null,
      "UserGravatar": "fef8a1875028f4300bb683f29c432894",
      "EditableText": "Haha, hentai is great... Although not all of it is tenticle rape.\n\nI personally don't have the perceverance to go downloading whole series etc, but my more favourite have been the normal.. Bit more sensuous.\nI'm going to have to get into full metal alchemist though - the series really did hit a nerve the other day, although I've only seen 90% of one episode, and a small music video.\n\n(FMA is not* hentai... as far as I know)",
      "EditableFormat": "bbcode",
      "HTML": "Haha, hentai is great... Although not all of it is tenticle rape.<br/><br/>I personally don't have the perceverance to go downloading whole series etc, but my more favourite have been the normal.. Bit more sensuous.<br/>I'm going to have to get into full metal alchemist though - the series really did hit a nerve the other day, although I've only seen 90% of one episode, and a small music video.<br/><br/>(FMA is not* hentai... as far as I know)",
      "PostDate": "2006-07-13T22:49:25+01:00",
      "LastEditDate": null
    },
    {
      "PostId": "9736",
      "UserId": 0,
      "Username": "The Unknown",
      "UserAvatar": null,
      "UserGravatar": "053bf459de65e0d1ab124323f312d185",
      "EditableText": "hentai maji de sugoi!",
      "EditableFormat": "bbcode",
      "HTML": "hentai maji de sugoi!",
      "PostDate": "2006-07-14T12:40:11+01:00",
      "LastEditDate": null
    },
    {
      "PostId": "9740",
      "UserId": 0,
      "Username": "paul_one",
      "UserAvatar": null,
      "UserGravatar": "fef8a1875028f4300bb683f29c432894",
      "EditableText": "OK - I can't get that translated at all..",
      "EditableFormat": "bbcode",
      "HTML": "OK - I can't get that translated at all..",
      "PostDate": "2006-07-14T12:47:01+01:00",
      "LastEditDate": null
    },
    {
      "PostId": "9748",
      "UserId": 0,
      "Username": "The Unknown",
      "UserAvatar": null,
      "UserGravatar": "053bf459de65e0d1ab124323f312d185",
      "EditableText": "[quote=&quot;Tr0n&quot;:2zu7101y]OK - I can't get that translated at all..[/quote:2zu7101y]\n\nloosely translated: Hentai is cool.\n\ndavidw wa baka ja nai, ne? <!-- s:lol: --><img src=\"{SMILIES_PATH}/icon_lol.gif\" alt=\":lol:\" title=\"Laughing\" /><!-- s:lol: -->",
      "EditableFormat": "bbcode",
      "HTML": "<blockquote><cite>Tr0n wrote:</cite>OK - I can't get that translated at all..</blockquote><br/><br/>loosely translated: Hentai is cool.<br/><br/>davidw wa baka ja nai, ne? <!-- s:lol: --><img src=\"{SMILIES_PATH}/icon_lol.gif\" alt=\":lol:\" title=\"Laughing\" /><!-- s:lol: -->",
      "PostDate": "2006-07-14T13:45:43+01:00",
      "LastEditDate": null
    },
    {
      "PostId": "9753",
      "UserId": 0,
      "Username": "davidw",
      "UserAvatar": null,
      "UserGravatar": "5d9c9199ac213c3e7284cd76a2262c4a",
      "EditableText": "Still making your silly comments, Unknown?\n\nMaybe I should post that PM you just sent me. I'm sure Alex would find it very interesting indeed.",
      "EditableFormat": "bbcode",
      "HTML": "Still making your silly comments, Unknown?<br/><br/>Maybe I should post that PM you just sent me. I'm sure Alex would find it very interesting indeed.",
      "PostDate": "2006-07-14T14:31:52+01:00",
      "LastEditDate": null
    },
    {
      "PostId": "9755",
      "UserId": 0,
      "Username": "The Unknown",
      "UserAvatar": null,
      "UserGravatar": "053bf459de65e0d1ab124323f312d185",
      "EditableText": "[quote=&quot;davidw&quot;:1h6hegj4]Still making your silly comments, Unknown?\n\nMaybe I should post that PM you just sent me. I'm sure Alex would find it very interesting indeed.[/quote:1h6hegj4]\n\nBaka yamero-yo Baka-mitai oshaberi\n\nYou might want to be careful what you post.  Alex  couldn't be upset with me. He'd be upset with you. That was in PM. I didn't post in here. If you post it in here you are provoking the wraith of Alex. Be advised, you think that you are unbannable.. you are in the same boat we are all in.....\n\n\nHottoite-kure-yo ~ leave me alone",
      "EditableFormat": "bbcode",
      "HTML": "<blockquote><cite>davidw wrote:</cite>Still making your silly comments, Unknown?<br/><br/>Maybe I should post that PM you just sent me. I'm sure Alex would find it very interesting indeed.</blockquote><br/><br/>Baka yamero-yo Baka-mitai oshaberi<br/><br/>You might want to be careful what you post.  Alex  couldn't be upset with me. He'd be upset with you. That was in PM. I didn't post in here. If you post it in here you are provoking the wraith of Alex. Be advised, you think that you are unbannable.. you are in the same boat we are all in.....<br/><br/><br/>Hottoite-kure-yo ~ leave me alone",
      "PostDate": "2006-07-14T15:54:02+01:00",
      "LastEditDate": null
    },
    {
      "PostId": "9759",
      "UserId": 0,
      "Username": "davidw",
      "UserAvatar": null,
      "UserGravatar": "5d9c9199ac213c3e7284cd76a2262c4a",
      "EditableText": "Your reasoning makes about as little sense as your &quot;I am The Buck&quot; posturing.",
      "EditableFormat": "bbcode",
      "HTML": "Your reasoning makes about as little sense as your &quot;I am The Buck&quot; posturing.",
      "PostDate": "2006-07-14T16:10:35+01:00",
      "LastEditDate": null
    },
    {
      "PostId": "9767",
      "UserId": 0,
      "Username": "The Unknown",
      "UserAvatar": null,
      "UserGravatar": "053bf459de65e0d1ab124323f312d185",
      "EditableText": "[quote=&quot;davidw&quot;:3puucty4]Your reasoning makes about as little sense as your &quot;I am The Buck&quot; posturing.[/quote:3puucty4]\nSHALLOW PEOPLE WITH SHALLOW MINDS FIND ONLY SHALLOW PLACES TO REST THEIR HEADS.\n\nI am the Buck",
      "EditableFormat": "bbcode",
      "HTML": "<blockquote><cite>davidw wrote:</cite>Your reasoning makes about as little sense as your &quot;I am The Buck&quot; posturing.</blockquote><br/>SHALLOW PEOPLE WITH SHALLOW MINDS FIND ONLY SHALLOW PLACES TO REST THEIR HEADS.<br/><br/>I am the Buck",
      "PostDate": "2006-07-14T19:25:01+01:00",
      "LastEditDate": null
    },
    {
      "PostId": "9771",
      "UserId": 0,
      "Username": "paul_one",
      "UserAvatar": null,
      "UserGravatar": "fef8a1875028f4300bb683f29c432894",
      "EditableText": "... or else they drown?",
      "EditableFormat": "bbcode",
      "HTML": "... or else they drown?",
      "PostDate": "2006-07-14T20:32:40+01:00",
      "LastEditDate": null
    },
    {
      "PostId": "9772",
      "UserId": 0,
      "Username": "The Unknown",
      "UserAvatar": null,
      "UserGravatar": "053bf459de65e0d1ab124323f312d185",
      "EditableText": "[quote=&quot;Tr0n&quot;:3rxnvn2a]... or else they drown?[/quote:3rxnvn2a]\n\nNo....They have scyophants that hang on their every word..... They find little minions to scurry about and lock threads and delete posts.",
      "EditableFormat": "bbcode",
      "HTML": "<blockquote><cite>Tr0n wrote:</cite>... or else they drown?</blockquote><br/><br/>No....They have scyophants that hang on their every word..... They find little minions to scurry about and lock threads and delete posts.",
      "PostDate": "2006-07-14T20:34:49+01:00",
      "LastEditDate": null
    },
    {
      "PostId": "9774",
      "UserId": 0,
      "Username": "davidw",
      "UserAvatar": null,
      "UserGravatar": "5d9c9199ac213c3e7284cd76a2262c4a",
      "EditableText": "Ah, so now I have sycophants hanging on my every word and minions locking and deleting threads for me? Geez...\n\nI wonder what I have to do to get one of my sycophants/minions to do the whole forum a favour and ban your sorry ass?",
      "EditableFormat": "bbcode",
      "HTML": "Ah, so now I have sycophants hanging on my every word and minions locking and deleting threads for me? Geez...<br/><br/>I wonder what I have to do to get one of my sycophants/minions to do the whole forum a favour and ban your sorry ass?",
      "PostDate": "2006-07-14T20:49:03+01:00",
      "LastEditDate": null
    },
    {
      "PostId": "9778",
      "UserId": 0,
      "Username": "paul_one",
      "UserAvatar": null,
      "UserGravatar": "fef8a1875028f4300bb683f29c432894",
      "EditableText": "I was going to try and split this - but then I'd only have 3 messages here, and another locked thread anyway... So I'm just flat out locking this because it's again turning into a war.\n[b:3vd6vyy6][LOCKED][/b:3vd6vyy6]",
      "EditableFormat": "bbcode",
      "HTML": "I was going to try and split this - but then I'd only have 3 messages here, and another locked thread anyway... So I'm just flat out locking this because it's again turning into a war.<br/><span style=\"font-weight:bold;\">[LOCKED]</span>",
      "PostDate": "2006-07-15T01:09:05+01:00",
      "LastEditDate": null
    }
  ]
}
