{
  "Topic": {
    "TopicId": "db1elzzmfuqq8z1n7s7xdw",
    "ForumId": "10",
    "Title": "Object Attributes and Saving",
    "LastUpdated": "2018-12-29T10:27:41.8989035Z",
    "ReplyCount": 0
  },
  "Posts": [
    {
      "PostId": "daded9fa-38c9-41bc-b2ad-9d9c0590a03a",
      "UserId": 142763,
      "Username": "Forgewright",
      "AvatarUrl": "http://i.imgur.com/Ea6HecZb.png",
      "UserAvatar": null,
      "UserGravatar": null,
      "EditableText": "If the start script is used to set the player or any object's attributes and during play the game is saved, what happens when the game is loaded? Will the start script erase any progress? ⚔\r\n",
      "EditableFormat": "markdown",
      "HTML": "<p>If the start script is used to set the player or any object's attributes and during play the game is saved, what happens when the game is loaded? Will the start script erase any progress? ⚔</p>\n\n",
      "PostDate": "2018-12-29T10:27:41.8989035Z",
      "LastEditDate": null,
      "link": null
    },
    {
      "PostId": "8cd94cc1-79af-49be-94db-5c8993ae6cec",
      "UserId": 319917,
      "Username": "mrangel",
      "AvatarUrl": "https://secure.gravatar.com/avatar/?d=retro",
      "UserAvatar": null,
      "UserGravatar": null,
      "EditableText": "The start script only runs when the game is first started.\r\n\r\nCode to set initial attributes belongs in the `start` or `_initialise_` scripts, and is run only once.\r\n\r\nCode that you want to run when the game is started or when it's loaded (such as using javascript to move things around in the browser, or adjusting settings based on if the game is running on mobile) goes in the UI initialisation script.",
      "EditableFormat": "markdown",
      "HTML": "<p>The start script only runs when the game is first started.</p>\n<p>Code to set initial attributes belongs in the <code>start</code> or <code>_initialise_</code> scripts, and is run only once.</p>\n<p>Code that you want to run when the game is started or when it's loaded (such as using javascript to move things around in the browser, or adjusting settings based on if the game is running on mobile) goes in the UI initialisation script.</p>\n\n",
      "PostDate": "2018-12-29T11:02:59.4078031Z",
      "LastEditDate": null,
      "link": null
    },
    {
      "PostId": "1b67e570-85a3-4c5f-8571-e619ada80ca9",
      "UserId": 142763,
      "Username": "Forgewright",
      "AvatarUrl": "http://i.imgur.com/Ea6HecZb.png",
      "UserAvatar": null,
      "UserGravatar": null,
      "EditableText": "Thanks Mrangel.",
      "EditableFormat": "markdown",
      "HTML": "<p>Thanks Mrangel.</p>\n\n",
      "PostDate": "2018-12-29T11:26:39.1041829Z",
      "LastEditDate": null,
      "link": null
    }
  ]
}
